<?xml version="1.0" encoding="utf-8"?>
<databaseChangeLog
        logicalFilePath="v0.1.0/changelog_account.xml"
        xmlns="http://www.liquibase.org/xml/ns/dbchangelog"
        xmlns:xsi="http://www.w3.org/2001/XMLSchema-instance"
        xsi:schemaLocation="http://www.liquibase.org/xml/ns/dbchangelog http://www.liquibase.org/xml/ns/dbchangelog/dbchangelog-4.11.xsd">

    <changeSet id="0_1_0_ACCOUNT_CONTACT_CREATE_TABLE" author="P70383">
        <comment>Create account_contact table</comment>
        <createTable tableName="account_contact" remarks="Represents an account contact">
            <column name="account_id" type="bigint" remarks="The account id where contact belongs to (foreign key to account table)">
                <constraints foreignKeyName="account_contact_account_fk" references="account(id)" nullable="false"
                             primaryKey="true" primaryKeyName="account_contact_pk" />
            </column>
            <column name="primary_contact" type="varchar(255)" remarks="The user for primary contact">
                <constraints nullable="false" />
            </column>
            <column name="secondary_contact" type="varchar(255)" remarks="The user for secondary contact">
                <constraints nullable="true" />
            </column>
            <column name="service_contact" type="varchar(255)" remarks="The user for service contact">
                <constraints nullable="false" />
            </column>
            <column name="financial_contact" type="varchar(255)" remarks="The user for financial contact">
                <constraints nullable="false" />
            </column>
            <column name="ca_site_contact" type="varchar(255)" remarks="The regulator user for site contact">
                <constraints nullable="true" />
            </column>
            <column name="vb_site_contact" type="varchar(255)" remarks="The verification body user for site contact">
                <constraints nullable="true" />
            </column>
        </createTable>
        <rollback>
            <sql>
                DROP TABLE IF EXISTS account_contact CASCADE;
            </sql>
        </rollback>
    </changeSet>

    <changeSet id="0_1_0_ACCOUNT_CONTACT_ADD_CA_SITE_CONTACT_IDX" author="P70383">
        <comment>Add ca_site_contact index for account_contact table</comment>
        <createIndex indexName="account_contact_ca_site_contact_idx" tableName="account_contact">
            <column name="ca_site_contact" />
        </createIndex>
        <rollback>
            <sql>
                DROP INDEX IF EXISTS account_contact_ca_site_contact_idx CASCADE
            </sql>
        </rollback>
    </changeSet>

    <changeSet id="0_1_0_ACCOUNT_CONTACT_ADD_VB_SITE_CONTACT_IDX" author="P70383">
        <comment>Add vb_site_contact index for account_contact table</comment>
        <createIndex indexName="account_contact_vb_site_contact_idx" tableName="account_contact">
            <column name="vb_site_contact" />
        </createIndex>
        <rollback>
            <sql>
                DROP INDEX IF EXISTS account_contact_vb_site_contact_idx CASCADE
            </sql>
        </rollback>
    </changeSet>
    
    <changeSet id="DROP_ACCOUNT_CONTACT_TABLE_AND_INDEXES" author="P35066">
    	<sql>
    		DROP TABLE IF EXISTS account_contact CASCADE;
    		DROP INDEX IF EXISTS account_contact_ca_site_contact_idx CASCADE;
    		DROP INDEX IF EXISTS account_contact_vb_site_contact_idx CASCADE;
    	</sql>
    </changeSet>
    
    <changeSet id="0_1_0_RECREATE_ACCOUNT_CONTACT_TABLE" author="P35066">
        <comment>Create account_contact type table</comment>
        <createTable tableName="account_contact" remarks="The account contact relationship table">
            <column name="account_id" type="bigint" remarks="The account id where contact belongs to (foreign key to account table)">
                 <constraints foreignKeyName="account_contact_acc_fk" references="account(id)" nullable="false" />
            </column>
            <column name="contact_type" type="varchar(255)" remarks="The type of the contact">
                <constraints nullable="false" />
            </column>
            <column name="user_id" type="varchar(255)" remarks="The user id responsible for the contact type">
                <constraints nullable="true" />
            </column>
        </createTable>
        <rollback>
            <sql>
                DROP TABLE IF EXISTS account_contact CASCADE;
            </sql>
        </rollback>
    </changeSet>

</databaseChangeLog>